agentbx/__init__.py
agentbx/__main__.py
agentbx/_version.py
agentbx/core/__init__.py
agentbx/core/agents/__init__.py
agentbx/core/agents/agent_security_manager.py
agentbx/core/agents/async_geometry_agent.py
agentbx/core/agents/sync_geometry_agent.py
agentbx/core/base_client.py
agentbx/core/bundle_base.py
agentbx/core/clients/__init__.py
agentbx/core/clients/array_translator.py
agentbx/core/clients/bfactor_optimizer.py
agentbx/core/clients/coordinate_optimizer.py
agentbx/core/clients/coordinate_translator.py
agentbx/core/clients/geometry_minimizer.py
agentbx/core/clients/optimization_client.py
agentbx/core/clients/solvent_optimizer.py
agentbx/core/config.py
agentbx/core/processors/__init__.py
agentbx/core/processors/base.py
agentbx/core/processors/experimental_data_processor.py
agentbx/core/processors/geometry_processor.py
agentbx/core/processors/gradient_processor.py
agentbx/core/processors/macromolecule_processor.py
agentbx/core/processors/structure_factor_processor.py
agentbx/core/processors/target_processor.py
agentbx/core/redis_manager.py
agentbx/core/redis_stream_manager.py
agentbx/py.typed
agentbx/schemas/__init__.py
agentbx/schemas/definitions/agent_configuration.yaml
agentbx/schemas/definitions/agent_security.yaml
agentbx/schemas/definitions/coordinate_update.yaml
agentbx/schemas/definitions/experimental_data.yaml
agentbx/schemas/definitions/geometry_gradient_data.yaml
agentbx/schemas/definitions/gradient_data.yaml
agentbx/schemas/definitions/macromolecule_data.yaml
agentbx/schemas/definitions/redis_streams.yaml
agentbx/schemas/definitions/structure_factor_data.yaml
agentbx/schemas/definitions/target_data.yaml
agentbx/schemas/definitions/xray_atomic_model_data.yaml
agentbx/schemas/generated.py
agentbx/schemas/generator.py
agentbx/utils/__init__.py
agentbx/utils/cli.py
agentbx/utils/data_analysis_utils.py
agentbx/utils/data_loader.py
agentbx/utils/generate_schemas.py
agentbx/utils/geometry_agent_cli.py
agentbx/utils/io/crystallographic_utils.py
agentbx-1.1.1.dist-info/LICENSE
agentbx-1.1.1.dist-info/METADATA
agentbx-1.1.1.dist-info/WHEEL
agentbx-1.1.1.dist-info/entry_points.txt
agentbx-1.1.1.dist-info/RECORD
