Metadata-Version: 2.3
Name: agentbx
Version: 1.1.1
Summary: Agentbx
License: MIT
Author: Petrus Zwart
Author-email: PHZwart@lbl.gov
Requires-Python: >=3.10,<4.0
Classifier: Development Status :: 3 - Alpha
Classifier: License :: OSI Approved :: MIT License
Classifier: Programming Language :: Python :: 3
Classifier: Programming Language :: Python :: 3.10
Classifier: Programming Language :: Python :: 3.11
Classifier: Programming Language :: Python :: 3.12
Classifier: Programming Language :: Python :: 3.13
Requires-Dist: PyYAML (>=6.0.0,<7.0.0)
Requires-Dist: click (>=8.0.1)
Requires-Dist: numpy (>=1.20.0,<2.0.0)
Requires-Dist: pydantic (>=2.0,<3.0)
Requires-Dist: redis (>=4.5.0,<5.0.0)
Requires-Dist: typing-extensions (>=4.0.0,<5.0.0)
Project-URL: Changelog, https://github.com/phzwart/agentbx/blob/main/CHANGELOG.md
Project-URL: Documentation, https://agentbx.readthedocs.io
Project-URL: Homepage, https://github.com/phzwart/agentbx
Project-URL: Repository, https://github.com/phzwart/agentbx
